{
    "session_id": "assignments-adni",
    "user_id": null,
    "memory": null,
    "session_data": {
        "session_state": {
            "mechanism_assignments_adni": [
                {
                    "mechanism": "Amyloid and Tau Pathology (ATN Pathway)",
                    "features": [
                        "CATVEGESC",
                        "DSPANBLTH",
                        "CDRSB",
                        "TRAASCOR",
                        "AVTOTB",
                        "AVDELTOT",
                        "CDGLOBAL",
                        "ANART",
                        "MMSE",
                        "FAQ",
                        "EcogSPPlan",
                        "Fusiform",
                        "EcogSPLang",
                        "AVTOT1",
                        "AV45",
                        "ICV",
                        "AVDEL30MIN",
                        "MOCA",
                        "CATANIMSC",
                        "ADAS11",
                        "ABETA42",
                        "COPYSCOR",
                        "DSPANFLTH",
                        "LDELTOTAL",
                        "ADAS13",
                        "AVTOT5",
                        "FBB",
                        "EcogSPOrgan",
                        "WholeBrain",
                        "EcogPtDivatt",
                        "CDRSB.1",
                        "ADASQ4",
                        "EcogPtTotal",
                        "DSPANBAC",
                        "CATANINTR",
                        "CATANPERS",
                        "mPACCtrailsB",
                        "Ventricles",
                        "Hippocampus",
                        "PIB",
                        "mPACCdigit",
                        "FDG",
                        "BNTTOTAL",
                        "ABETA40",
                        "AVTOT4",
                        "MINTTOTAL",
                        "EcogSPVisspat",
                        "RAVLT_perc_forgetting",
                        "EcogSPMem",
                        "TAU",
                        "PTAU",
                        "AVTOT6",
                        "EcogPtLang",
                        "EcogPtPlan",
                        "RAVLT_immediate",
                        "AVTOT2",
                        "RAVLT_forgetting",
                        "EcogPtOrgan",
                        "CATVGPERS",
                        "EcogPtVisspat",
                        "TRABSCOR",
                        "Entorhinal",
                        "CLOCKSCOR",
                        "DIGITSCOR",
                        "MidTemp",
                        "RAVLT_learning",
                        "EcogSPTotal",
                        "CATVGINTR",
                        "EcogSPDivatt",
                        "DSPANFOR",
                        "AVTOT3",
                        "MMSCORE",
                        "EcogPtMem"
                    ],
                    "explanation": "Amyloid and tau pathology are directly measured by CSF biomarkers (ABETA40, ABETA42, TAU, PTAU) and amyloid PET imaging (PIB, AV45, FBB). These pathologies cause neurodegeneration, which is reflected in structural MRI (Hippocampus, Entorhinal, WholeBrain, Fusiform, MidTemp, Ventricles, ICV) and FDG-PET (FDG). Cognitive and functional tests (MMSE, MOCA, ADAS, RAVLT, LDELTOTAL, FAQ, CDRSB, CDRSB.1, CDGLOBAL, EcogPt*, EcogSP*) are impacted by the downstream effects of amyloid and tau accumulation. Many neuropsychological tests (MMSCORE, CLOCKSCOR, COPYSCOR, AVLT, Digit Span, Category Fluency, Trails, DSST, BNT, ANART, MINT, mPACCdigit, mPACCtrailsB) are sensitive to the cognitive decline resulting from these pathologies."
                },
                {
                    "mechanism": "Neurodegeneration and Brain Atrophy",
                    "features": [
                        "CATVEGESC",
                        "DSPANBLTH",
                        "CDRSB",
                        "TRAASCOR",
                        "AVTOTB",
                        "AVDELTOT",
                        "CDGLOBAL",
                        "ANART",
                        "MMSE",
                        "FAQ",
                        "EcogSPPlan",
                        "Fusiform",
                        "EcogSPLang",
                        "AVTOT1",
                        "ICV",
                        "AVDEL30MIN",
                        "MOCA",
                        "CATANIMSC",
                        "ADAS11",
                        "COPYSCOR",
                        "DSPANFLTH",
                        "LDELTOTAL",
                        "ADAS13",
                        "AVTOT5",
                        "EcogSPOrgan",
                        "WholeBrain",
                        "EcogPtDivatt",
                        "CDRSB.1",
                        "ADASQ4",
                        "EcogPtTotal",
                        "DSPANBAC",
                        "CATANINTR",
                        "CATANPERS",
                        "mPACCtrailsB",
                        "Ventricles",
                        "Hippocampus",
                        "mPACCdigit",
                        "FDG",
                        "BNTTOTAL",
                        "AVTOT4",
                        "MINTTOTAL",
                        "EcogSPVisspat",
                        "RAVLT_perc_forgetting",
                        "EcogSPMem",
                        "AVTOT6",
                        "EcogPtLang",
                        "EcogPtPlan",
                        "RAVLT_immediate",
                        "AVTOT2",
                        "RAVLT_forgetting",
                        "EcogPtOrgan",
                        "CATVGPERS",
                        "EcogPtVisspat",
                        "TRABSCOR",
                        "Entorhinal",
                        "CLOCKSCOR",
                        "DIGITSCOR",
                        "MidTemp",
                        "RAVLT_learning",
                        "EcogSPTotal",
                        "CATVGINTR",
                        "EcogSPDivatt",
                        "DSPANFOR",
                        "AVTOT3",
                        "MMSCORE",
                        "EcogPtMem"
                    ],
                    "explanation": "Neurodegeneration and brain atrophy are directly measured by MRI (Hippocampus, Entorhinal, WholeBrain, Fusiform, MidTemp, Ventricles, ICV) and FDG-PET (FDG). These changes lead to cognitive and functional decline, captured by cognitive tests (MMSE, MOCA, ADAS, RAVLT, LDELTOTAL, FAQ, CDRSB, CDRSB.1, CDGLOBAL, EcogPt*, EcogSP*) and neuropsychological batteries (MMSCORE, CLOCKSCOR, COPYSCOR, AVLT, Digit Span, Category Fluency, Trails, DSST, BNT, ANART, MINT, mPACCdigit, mPACCtrailsB)."
                },
                {
                    "mechanism": "Cognitive and Functional Decline",
                    "features": [
                        "CATVEGESC",
                        "DSPANBLTH",
                        "NPIDSEV",
                        "CDRSB",
                        "TRAASCOR",
                        "NPIGSEV",
                        "AVTOTB",
                        "AVDELTOT",
                        "CDGLOBAL",
                        "NPIASEV",
                        "ANART",
                        "MMSE",
                        "FAQ",
                        "NPISCORE",
                        "EcogSPPlan",
                        "EcogSPLang",
                        "AVTOT1",
                        "NPIBSEV",
                        "NPIHSEV",
                        "AVDEL30MIN",
                        "NPICSEV",
                        "MOCA",
                        "CATANIMSC",
                        "ADAS11",
                        "COPYSCOR",
                        "NPILSEV",
                        "DSPANFLTH",
                        "NPIFSEV",
                        "LDELTOTAL",
                        "ADAS13",
                        "AVTOT5",
                        "EcogSPOrgan",
                        "EcogPtDivatt",
                        "GDTOTAL",
                        "CDRSB.1",
                        "ADASQ4",
                        "EcogPtTotal",
                        "DSPANBAC",
                        "CATANINTR",
                        "CATANPERS",
                        "mPACCtrailsB",
                        "mPACCdigit",
                        "BNTTOTAL",
                        "NPIKSEV",
                        "AVTOT4",
                        "MINTTOTAL",
                        "EcogSPVisspat",
                        "RAVLT_perc_forgetting",
                        "EcogSPMem",
                        "AVTOT6",
                        "NPIISEV",
                        "NPIJSEV",
                        "EcogPtLang",
                        "EcogPtPlan",
                        "NPIESEV",
                        "RAVLT_immediate",
                        "AVTOT2",
                        "EcogPtOrgan",
                        "RAVLT_forgetting",
                        "CATVGPERS",
                        "EcogPtVisspat",
                        "TRABSCOR",
                        "CLOCKSCOR",
                        "DIGITSCOR",
                        "RAVLT_learning",
                        "EcogSPTotal",
                        "CATVGINTR",
                        "EcogSPDivatt",
                        "DSPANFOR",
                        "AVTOT3",
                        "MMSCORE",
                        "EcogPtMem"
                    ],
                    "explanation": "Cognitive and functional decline is measured by global and domain-specific cognitive tests (MMSE, MOCA, ADAS, RAVLT, LDELTOTAL, FAQ, CDRSB, CDRSB.1, CDGLOBAL, EcogPt*, EcogSP*), as well as neuropsychological batteries (MMSCORE, CLOCKSCOR, COPYSCOR, AVLT, Digit Span, Category Fluency, Trails, DSST, BNT, ANART, MINT, mPACCdigit, mPACCtrailsB). Neuropsychiatric symptoms (NPI-Q, GDS) can also impact function and cognition."
                },
                {
                    "mechanism": "Neuropsychiatric Symptoms and Network Dysfunction",
                    "features": [
                        "NPIASEV",
                        "NPIBSEV",
                        "NPICSEV",
                        "NPIDSEV",
                        "NPIESEV",
                        "NPIFSEV",
                        "NPIGSEV",
                        "NPIHSEV",
                        "NPIISEV",
                        "NPIJSEV",
                        "NPIKSEV",
                        "NPILSEV",
                        "NPISCORE",
                        "GDTOTAL",
                        "CDGLOBAL",
                        "CDRSB",
                        "CDRSB.1",
                        "FAQ",
                        "MOCA",
                        "MMSE",
                        "ADAS11",
                        "ADAS13",
                        "ADASQ4",
                        "EcogPtMem",
                        "EcogPtLang",
                        "EcogPtVisspat",
                        "EcogPtPlan",
                        "EcogPtOrgan",
                        "EcogPtDivatt",
                        "EcogPtTotal",
                        "EcogSPMem",
                        "EcogSPLang",
                        "EcogSPVisspat",
                        "EcogSPPlan",
                        "EcogSPOrgan",
                        "EcogSPDivatt",
                        "EcogSPTotal",
                        "FDG",
                        "Hippocampus",
                        "Entorhinal",
                        "WholeBrain",
                        "Fusiform",
                        "MidTemp",
                        "Ventricles",
                        "RAVLT_immediate",
                        "RAVLT_learning",
                        "RAVLT_forgetting",
                        "RAVLT_perc_forgetting",
                        "LDELTOTAL"
                    ],
                    "explanation": "Neuropsychiatric symptoms are directly measured by the NPI-Q (NPIASEV–NPILSEV, NPISCORE) and GDS (GDTOTAL). These symptoms are linked to network dysfunction and atrophy (FDG, MRI measures), and can impact global and domain-specific cognition and function (CDGLOBAL, CDRSB, FAQ, MOCA, MMSE, ADAS, EcogPt*, EcogSP*, RAVLT, LDELTOTAL)."
                },
                {
                    "mechanism": "Vascular Dysfunction and Cerebrovascular Disease",
                    "features": [
                        "VSBPSYS",
                        "VSBPDIA",
                        "VSPULSE",
                        "VSRESP",
                        "VSWEIGHT",
                        "VSHEIGHT",
                        "AGE",
                        "Hippocampus",
                        "Entorhinal",
                        "WholeBrain",
                        "Fusiform",
                        "MidTemp",
                        "Ventricles",
                        "ICV",
                        "FDG",
                        "ABETA40",
                        "ABETA42",
                        "TAU",
                        "PTAU",
                        "MOCA",
                        "MMSE",
                        "ADAS11",
                        "ADAS13",
                        "ADASQ4",
                        "FAQ",
                        "CDRSB",
                        "CDRSB.1",
                        "CDGLOBAL",
                        "EcogPtMem",
                        "EcogPtLang",
                        "EcogPtVisspat",
                        "EcogPtPlan",
                        "EcogPtOrgan",
                        "EcogPtDivatt",
                        "EcogPtTotal",
                        "EcogSPMem",
                        "EcogSPLang",
                        "EcogSPVisspat",
                        "EcogSPPlan",
                        "EcogSPOrgan",
                        "EcogSPDivatt",
                        "EcogSPTotal"
                    ],
                    "explanation": "Vascular dysfunction is measured by blood pressure (VSBPSYS, VSBPDIA), pulse (VSPULSE), respiration (VSRESP), and anthropometrics (VSWEIGHT, VSHEIGHT). Age is a major vascular risk factor. Vascular health impacts brain structure (MRI), metabolism (FDG), and can influence amyloid and tau pathology (ABETA40, ABETA42, TAU, PTAU). Cognitive and functional measures (MOCA, MMSE, ADAS, FAQ, CDRSB, CDGLOBAL, EcogPt*, EcogSP*) are affected by vascular contributions to neurodegeneration."
                },
                {
                    "mechanism": "Genetic and Proteomic Risk Factors",
                    "features": [
                        "AGE",
                        "PTEDUCAT",
                        "PTETHCAT",
                        "PTGENDER",
                        "PTMARRY",
                        "PTRACCAT",
                        "ABETA40",
                        "ABETA42",
                        "TAU",
                        "PTAU",
                        "PIB",
                        "AV45",
                        "FBB",
                        "FDG",
                        "Hippocampus",
                        "Entorhinal",
                        "WholeBrain",
                        "Fusiform",
                        "MidTemp",
                        "Ventricles",
                        "ICV",
                        "MOCA",
                        "MMSE",
                        "ADAS11",
                        "ADAS13",
                        "ADASQ4",
                        "FAQ",
                        "CDRSB",
                        "CDRSB.1",
                        "CDGLOBAL",
                        "EcogPtMem",
                        "EcogPtLang",
                        "EcogPtVisspat",
                        "EcogPtPlan",
                        "EcogPtOrgan",
                        "EcogPtDivatt",
                        "EcogPtTotal",
                        "EcogSPMem",
                        "EcogSPLang",
                        "EcogSPVisspat",
                        "EcogSPPlan",
                        "EcogSPOrgan",
                        "EcogSPDivatt",
                        "EcogSPTotal"
                    ],
                    "explanation": "Genetic and proteomic risk factors (e.g., APOE4, not directly listed but reflected in demographic variables and biofluid markers) influence amyloid and tau pathology (ABETA40, ABETA42, TAU, PTAU, PIB, AV45, FBB), neurodegeneration (MRI, FDG), and clinical presentation (cognitive and functional measures). Demographic variables (AGE, PTEDUCAT, PTETHCAT, PTGENDER, PTMARRY, PTRACCAT) are proxies for genetic background and risk stratification."
                },
                {
                    "mechanism": "Demographic and Cognitive Reserve Modifiers",
                    "features": [
                        "CATVEGESC",
                        "DSPANBLTH",
                        "ADASQ4",
                        "EcogPtTotal",
                        "DSPANBAC",
                        "CATANINTR",
                        "CDRSB",
                        "PTETHCAT",
                        "TRAASCOR",
                        "CATANPERS",
                        "PTMARRY",
                        "mPACCtrailsB",
                        "AVTOTB",
                        "AVDELTOT",
                        "CDGLOBAL",
                        "VSPULSE",
                        "ANART",
                        "MMSE",
                        "FAQ",
                        "mPACCdigit",
                        "BNTTOTAL",
                        "VSHEIGHT",
                        "EcogSPPlan",
                        "EcogSPLang",
                        "AVTOT1",
                        "AGE",
                        "AVTOT4",
                        "PTRACCAT",
                        "VSWEIGHT",
                        "AVDEL30MIN",
                        "PTEDUCAT",
                        "MOCA",
                        "MINTTOTAL",
                        "EcogSPVisspat",
                        "CATANIMSC",
                        "ADAS11",
                        "EcogSPMem",
                        "AVTOT6",
                        "EcogPtLang",
                        "PTGENDER",
                        "EcogPtPlan",
                        "VSBPDIA",
                        "COPYSCOR",
                        "AVTOT2",
                        "EcogPtOrgan",
                        "DSPANFLTH",
                        "CATVGPERS",
                        "VSRESP",
                        "EcogPtVisspat",
                        "TRABSCOR",
                        "CLOCKSCOR",
                        "DIGITSCOR",
                        "CDRSB.1",
                        "EcogSPTotal",
                        "ADAS13",
                        "AVTOT5",
                        "CATVGINTR",
                        "EcogSPOrgan",
                        "EcogSPDivatt",
                        "EcogPtDivatt",
                        "DSPANFOR",
                        "AVTOT3",
                        "MMSCORE",
                        "EcogPtMem",
                        "VSBPSYS"
                    ],
                    "explanation": "Demographic factors (AGE, PTEDUCAT, PTETHCAT, PTGENDER, PTMARRY, PTRACCAT) and physical health (VSWEIGHT, VSHEIGHT, VSBPSYS, VSBPDIA, VSPULSE, VSRESP) influence cognitive reserve and risk. Cognitive and functional measures (MOCA, MMSE, ADAS, FAQ, CDRSB, CDGLOBAL, EcogPt*, EcogSP*, neuropsychological tests) are modulated by these factors, affecting the clinical manifestation of AD pathology."
                }
            ]
        }
    },
    "extra_data": null,
    "created_at": null,
    "updated_at": 1748946385,
    "workflow_id": "30920fd1-fc6e-4f7e-b6a5-3f5f5e0bc0e4",
    "workflow_data": {
        "name": "MechanismFeatureAssignmentWorkflow",
        "workflow_id": "30920fd1-fc6e-4f7e-b6a5-3f5f5e0bc0e4",
        "description": "Assigns features to disease mechanisms."
    }
}